taboo/__init__.py
taboo/attacker.py
taboo/checker.py
taboo/defender.py
taboo/formatter.py
taboo/judger.py
taboo/ruler.py
taboo/util.py
xcj-0.0.1.dist-info/LICENSE
xcj-0.0.1.dist-info/METADATA
xcj-0.0.1.dist-info/WHEEL
xcj-0.0.1.dist-info/top_level.txt
xcj-0.0.1.dist-info/RECORD
