Metadata-Version: 2.1
Name: xcj
Version: 0.0.1
Summary: Codes for taboo.
Home-page: https://github.com/haoxizhong/taboo
Author: Zhong Haoxi
Author-email: zhonghaoxi@yeah.net
License: UNKNOWN
Platform: UNKNOWN
Classifier: Programming Language :: Python :: 3
Classifier: License :: OSI Approved :: MIT License
Classifier: Operating System :: OS Independent
Requires-Python: >=3.5
